db_automation_PYPI/__init__.py
db_automation_PYPI/mongo_crud.py
db_automation_PYPI-0.0.4.dist-info/LICENSE
db_automation_PYPI-0.0.4.dist-info/METADATA
db_automation_PYPI-0.0.4.dist-info/WHEEL
db_automation_PYPI-0.0.4.dist-info/top_level.txt
db_automation_PYPI-0.0.4.dist-info/RECORD
